pandasflow/__init__.py
pandasflow/get_import.py
pandasflow/get_news.py
pandasflow/get_psql.py
pandasflow/get_sqlt.py
pandasflow/reset_mi.py
pandasflow/dev/__init__.py
pandasflow/dev/err_mean_diff.py
pandasflow/metrics/__init__.py
pandasflow/metrics/conf_mat.py
pandasflow/metrics/lloss_up.py
pandasflow/metrics/mean_error.py
pandasflow/metrics/metrics_class.py
pandasflow/metrics/precision_recall.py
pandasflow/metrics/roc_auc.py
pandasflow/model/__init__.py
pandasflow/model/best_thr_f1.py
pandasflow/model/calc_class_from_score.py
pandasflow/services/__init__.py
pandasflow/services/rmsle.py
pandasflow/services/smape.py
pandasflow/services/wape.py
pandasflow/split/__init__.py
pandasflow/split/inherit_train_test.py
pandasflow/split/inherit_train_valid_test.py
pandasflow/split/train_test.py
pandasflow/split/train_valid_test.py
test/__init__.py
test/best_thr_f1_test.py
test/calc_class_from_score_test.py
test/conf_mat_test.py
test/get_news_test.py
test/lloss_up_test.py
test/mean_error_test.py
test/metrics_class_test.py
test/precision_recall_test.py
test/roc_auc_test.py
test/split_itt_test.py
test/split_itvt_test.py
test/split_tt_test.py
test/split_tvt_test.py
pandasflow-0.10.1.dist-info/LICENCE
pandasflow-0.10.1.dist-info/METADATA
pandasflow-0.10.1.dist-info/WHEEL
pandasflow-0.10.1.dist-info/top_level.txt
pandasflow-0.10.1.dist-info/RECORD
