Metadata-Version: 2.1
Name: pandasflow
Version: 0.10.1
Summary: A set of custom python modules for friendly workflow on pandas
Home-page: https://github.com/Priboy313/pandasflow
Author: Priboy313
Author-email: Priboy313@yandex.ru
License: UNKNOWN
Platform: UNKNOWN
Classifier: Programming Language :: Python :: 3.10
Classifier: License :: OSI Approved :: GNU General Public License v3 (GPLv3)
License-File: LICENCE
Requires-Dist: pandas
Requires-Dist: scikit-learn
Requires-Dist: phik
Requires-Dist: shap
Requires-Dist: tqdm
